nadoo_migration_framework/__init__.py
nadoo_migration_framework/analyzers.py
nadoo_migration_framework/base.py
nadoo_migration_framework/cli.py
nadoo_migration_framework/compatibility.py
nadoo_migration_framework/config.py
nadoo_migration_framework/dependency_management.py
nadoo_migration_framework/frameworks/__init__.py
nadoo_migration_framework/frameworks/django.py
nadoo_migration_framework/frameworks/django_analyzer.py
nadoo_migration_framework/frameworks/django_fixer.py
nadoo_migration_framework/frameworks/django_functional_migrator.py
nadoo_migration_framework/frameworks/django_utils.py
nadoo_migration_framework/frameworks/flask.py
nadoo_migration_framework/frameworks/nadoo_launchpad.py
nadoo_migration_framework/frameworks/toga_app.py
nadoo_migration_framework/frameworks/toga_functional_migrator.py
nadoo_migration_framework/functions/__init__.py
nadoo_migration_framework/functions/code_analysis.py
nadoo_migration_framework/functions/dependency_analysis.py
nadoo_migration_framework/functions/project_structure.py
nadoo_migration_framework/manager.py
nadoo_migration_framework/migration_manager.py
nadoo_migration_framework/migrations/__init__.py
nadoo_migration_framework/migrations/briefcase_migrations.py
nadoo_migration_framework/migrations/database_migrations.py
nadoo_migration_framework/migrations/migration_engine.py
nadoo_migration_framework/migrations/nadoo_launchpad_migrations.py
nadoo_migration_framework/migrations/toga_functional_migrations.py
nadoo_migration_framework/migrations/toga_import_migrations.py
nadoo_migration_framework/migrations/toga_migrations.py
nadoo_migration_framework/migrations.py
nadoo_migration_framework/templates.py
nadoo_migration_framework/version_compatibility.py
nadoo_migration_framework/version_management.py
nadoo_migration_framework/version_types.py
nadoo_migration_framework-0.2.1.dist-info/LICENSE
nadoo_migration_framework-0.2.1.dist-info/METADATA
nadoo_migration_framework-0.2.1.dist-info/WHEEL
nadoo_migration_framework-0.2.1.dist-info/entry_points.txt
nadoo_migration_framework-0.2.1.dist-info/RECORD
