Metadata-Version: 2.1
Name: nadoo-migration-framework
Version: 0.2.1
Summary: A powerful, Git-based migration framework for NADOO Framework projects
Home-page: https://github.com/NADOOIT/nadoo-migration-framework
License: MIT
Keywords: nadoo,migration,framework
Author: NADOO IT
Author-email: info@nadoo.it
Requires-Python: >=3.8,<4.0
Classifier: Development Status :: 4 - Beta
Classifier: Intended Audience :: Developers
Classifier: License :: OSI Approved :: MIT License
Classifier: Programming Language :: Python :: 3
Classifier: Programming Language :: Python :: 3.8
Classifier: Programming Language :: Python :: 3.9
Classifier: Programming Language :: Python :: 3.10
Classifier: Programming Language :: Python :: 3.11
Classifier: Programming Language :: Python :: 3.12
Classifier: Programming Language :: Python :: 3.13
Classifier: Topic :: Software Development :: Libraries :: Python Modules
Requires-Dist: click (>=8.1.0,<9.0.0)
Requires-Dist: pathlib (>=1.0.1,<2.0.0)
Requires-Dist: toml (>=0.10.2,<0.11.0)
Project-URL: Documentation, https://github.com/NADOOIT/nadoo-migration-framework#readme
Project-URL: Repository, https://github.com/NADOOIT/nadoo-migration-framework
